{
  "version": "2026-05-20",
  "principles": [
    "Original CampIn icons only; do not copy Airbnb icon shapes or campaign artwork.",
    "24x24 line icons, rounded caps, currentColor, clear labels.",
    "Use icons to improve decisions, not as decoration."
  ],
  "icons": [
    { "id": "tent", "family": "stay", "label": "Tent pitch", "primaryUse": "Campsite category and listing cards" },
    { "id": "own-tent", "family": "stay", "label": "Own tent friendly", "primaryUse": "Filter for campers bringing gear" },
    { "id": "farm-camp", "family": "stay", "label": "Farm camp", "primaryUse": "Private farmland stays" },
    { "id": "forest-edge", "family": "stay", "label": "Forest edge", "primaryUse": "Nature-edge stays with permission notes" },
    { "id": "lake-nearby", "family": "stay", "label": "Lake nearby", "primaryUse": "Water-nearby discovery with safety caveat" },
    { "id": "hill-view", "family": "stay", "label": "Hill view", "primaryUse": "Highland and viewpoint stays" },
    { "id": "road-stop", "family": "road", "label": "Road stop", "primaryUse": "Route support places" },
    { "id": "parking", "family": "road", "label": "Parking", "primaryUse": "Vehicle parking amenity" },
    { "id": "bike", "family": "road", "label": "Bike friendly", "primaryUse": "Motorcycle route and access filter" },
    { "id": "campervan", "family": "road", "label": "Campervan access", "primaryUse": "Van and campervan route support" },
    { "id": "route", "family": "road", "label": "Route", "primaryUse": "Trip itinerary and road pages" },
    { "id": "signal", "family": "road", "label": "Phone signal", "primaryUse": "Network availability notes" },
    { "id": "washroom", "family": "amenity", "label": "Washroom", "primaryUse": "Critical listing amenity" },
    { "id": "shower", "family": "amenity", "label": "Shower", "primaryUse": "Bathing facility" },
    { "id": "water", "family": "amenity", "label": "Water", "primaryUse": "Drinking or usable water" },
    { "id": "power", "family": "amenity", "label": "Power", "primaryUse": "Charging and electricity" },
    { "id": "food", "family": "amenity", "label": "Food", "primaryUse": "Food or kitchen support" },
    { "id": "fire-safe", "family": "amenity", "label": "Fire-safe zone", "primaryUse": "Fire permission and restrictions" },
    { "id": "first-aid", "family": "amenity", "label": "First aid", "primaryUse": "Basic safety readiness" },
    { "id": "reviewed", "family": "trust", "label": "CampIn reviewed", "primaryUse": "Earned trust badge" },
    { "id": "permission", "family": "trust", "label": "Permission status", "primaryUse": "Legal/local permission signal" },
    { "id": "exact-pin", "family": "trust", "label": "Exact pin", "primaryUse": "Location confidence" },
    { "id": "host-present", "family": "trust", "label": "Host present", "primaryUse": "Caretaker/host availability" },
    { "id": "women-aware", "family": "trust", "label": "Women-aware host", "primaryUse": "Host process for women/couples safety concerns" },
    { "id": "family-safe", "family": "trust", "label": "Family safe", "primaryUse": "Family-suitable listing signal" },
    { "id": "quiet-zone", "family": "trust", "label": "Quiet zone", "primaryUse": "Low-noise stay expectation" },
    { "id": "emergency-contact", "family": "trust", "label": "Emergency contact", "primaryUse": "Emergency contact availability" },
    { "id": "search", "family": "action", "label": "Search", "primaryUse": "Search controls" },
    { "id": "filter", "family": "action", "label": "Filter", "primaryUse": "Filter controls" },
    { "id": "save", "family": "action", "label": "Save", "primaryUse": "Shortlisting" },
    { "id": "share", "family": "action", "label": "Share", "primaryUse": "Sharing route/listing" },
    { "id": "apply", "family": "action", "label": "Apply", "primaryUse": "Host or road-stop application" },
    { "id": "export", "family": "action", "label": "Export", "primaryUse": "Lead export" },
    { "id": "score", "family": "action", "label": "Score", "primaryUse": "Validation score" },
    { "id": "message", "family": "action", "label": "Message", "primaryUse": "CampChat or contact" },
    { "id": "newsletter", "family": "action", "label": "Newsletter", "primaryUse": "The Campfire signup" }
  ]
}
